{
  "platforms": [
    {
      "x": 260,
      "y": 500,
      "w": 204,
      "h": 24,
      "type": "fall"
    },
    {
      "x": 639,
      "y": 563,
      "w": 214,
      "h": 24,
      "type": "normal"
    },
    {
      "x": 985,
      "y": 610,
      "w": 248,
      "h": 24,
      "type": "normal"
    },
    {
      "x": 1382,
      "y": 481,
      "w": 248,
      "h": 24,
      "type": "fragile"
    },
    {
      "x": 1740,
      "y": 518,
      "w": 203,
      "h": 24,
      "type": "fragile"
    },
    {
      "x": 2111,
      "y": 605,
      "w": 180,
      "h": 24,
      "type": "normal"
    },
    {
      "x": 2383,
      "y": 513,
      "w": 185,
      "h": 24,
      "type": "normal"
    },
    {
      "x": 2678,
      "y": 570,
      "w": 250,
      "h": 24,
      "type": "normal"
    },
    {
      "x": 3085,
      "y": 629,
      "w": 216,
      "h": 24,
      "type": "fall"
    },
    {
      "x": 3445,
      "y": 510,
      "w": 249,
      "h": 24,
      "type": "normal"
    },
    {
      "x": 3832,
      "y": 582,
      "w": 217,
      "h": 24,
      "type": "normal"
    },
    {
      "x": 4176,
      "y": 652,
      "w": 190,
      "h": 24,
      "type": "bounce"
    },
    {
      "x": 4462,
      "y": 467,
      "w": 204,
      "h": 24,
      "type": "normal"
    },
    {
      "x": 4858,
      "y": 540,
      "w": 200,
      "h": 24,
      "type": "fall"
    },
    {
      "x": 5213,
      "y": 620,
      "w": 240,
      "h": 24,
      "type": "normal"
    },
    {
      "x": 5552,
      "y": 461,
      "w": 219,
      "h": 24,
      "type": "bounce"
    },
    {
      "x": 5954,
      "y": 535,
      "w": 208,
      "h": 24,
      "type": "normal"
    },
    {
      "x": 6360,
      "y": 663,
      "w": 230,
      "h": 24,
      "type": "normal"
    },
    {
      "x": 6724,
      "y": 494,
      "w": 229,
      "h": 24,
      "type": "normal"
    }
  ],
  "coins": [
    {
      "x": 345,
      "y": 460
    },
    {
      "x": 378,
      "y": 438
    },
    {
      "x": 733,
      "y": 523
    },
    {
      "x": 746,
      "y": 501
    },
    {
      "x": 1097,
      "y": 570
    },
    {
      "x": 1093,
      "y": 548
    },
    {
      "x": 1514,
      "y": 441
    },
    {
      "x": 1490,
      "y": 419
    },
    {
      "x": 1844,
      "y": 478
    },
    {
      "x": 1826,
      "y": 456
    },
    {
      "x": 2182,
      "y": 565
    },
    {
      "x": 2184,
      "y": 543
    },
    {
      "x": 3562,
      "y": 470
    },
    {
      "x": 3579,
      "y": 448
    },
    {
      "x": 3922,
      "y": 542
    },
    {
      "x": 3926,
      "y": 520
    },
    {
      "x": 4260,
      "y": 612
    },
    {
      "x": 4279,
      "y": 590
    },
    {
      "x": 4954,
      "y": 500
    },
    {
      "x": 4950,
      "y": 478
    },
    {
      "x": 5332,
      "y": 580
    },
    {
      "x": 5321,
      "y": 558
    },
    {
      "x": 6073,
      "y": 495
    },
    {
      "x": 6047,
      "y": 473
    },
    {
      "x": 6846,
      "y": 454
    },
    {
      "x": 6836,
      "y": 432
    }
  ],
  "enemies": [
    {
      "x": 302,
      "y": 490,
      "kind": "jumper"
    },
    {
      "x": 714,
      "y": 553,
      "kind": "walker"
    },
    {
      "x": 1171,
      "y": 600,
      "kind": "walker"
    },
    {
      "x": 1782,
      "y": 398,
      "kind": "flyer"
    },
    {
      "x": 2193,
      "y": 595,
      "kind": "walker"
    },
    {
      "x": 2481,
      "y": 503,
      "kind": "jumper"
    },
    {
      "x": 2845,
      "y": 560,
      "kind": "jumper"
    },
    {
      "x": 3166,
      "y": 619,
      "kind": "walker"
    },
    {
      "x": 3561,
      "y": 500,
      "kind": "walker"
    },
    {
      "x": 3995,
      "y": 572,
      "kind": "walker"
    },
    {
      "x": 4214,
      "y": 642,
      "kind": "jumper"
    },
    {
      "x": 4539,
      "y": 457,
      "kind": "walker"
    },
    {
      "x": 4909,
      "y": 420,
      "kind": "flyer"
    },
    {
      "x": 5281,
      "y": 610,
      "kind": "jumper"
    },
    {
      "x": 5611,
      "y": 451,
      "kind": "jumper"
    },
    {
      "x": 6085,
      "y": 415,
      "kind": "flyer"
    },
    {
      "x": 6501,
      "y": 653,
      "kind": "walker"
    }
  ]
}