{
  "platforms": [
    {
      "x": 260,
      "y": 506,
      "w": 226,
      "h": 24,
      "type": "normal"
    },
    {
      "x": 670,
      "y": 534,
      "w": 222,
      "h": 24,
      "type": "fragile"
    },
    {
      "x": 1057,
      "y": 589,
      "w": 260,
      "h": 24,
      "type": "normal"
    },
    {
      "x": 1443,
      "y": 499,
      "w": 213,
      "h": 24,
      "type": "bounce"
    },
    {
      "x": 1842,
      "y": 582,
      "w": 180,
      "h": 24,
      "type": "normal"
    },
    {
      "x": 2210,
      "y": 642,
      "w": 181,
      "h": 24,
      "type": "fall"
    },
    {
      "x": 2486,
      "y": 524,
      "w": 238,
      "h": 24,
      "type": "normal"
    },
    {
      "x": 2918,
      "y": 520,
      "w": 227,
      "h": 24,
      "type": "normal"
    },
    {
      "x": 3308,
      "y": 615,
      "w": 189,
      "h": 24,
      "type": "normal"
    },
    {
      "x": 3671,
      "y": 496,
      "w": 186,
      "h": 24,
      "type": "normal"
    },
    {
      "x": 3950,
      "y": 550,
      "w": 198,
      "h": 24,
      "type": "normal"
    }
  ],
  "coins": [
    {
      "x": 379,
      "y": 466
    },
    {
      "x": 369,
      "y": 444
    },
    {
      "x": 775,
      "y": 494
    },
    {
      "x": 799,
      "y": 472
    },
    {
      "x": 1181,
      "y": 549
    },
    {
      "x": 1540,
      "y": 459
    },
    {
      "x": 1565,
      "y": 437
    },
    {
      "x": 1932,
      "y": 542
    },
    {
      "x": 1941,
      "y": 520
    },
    {
      "x": 2310,
      "y": 602
    },
    {
      "x": 2599,
      "y": 484
    },
    {
      "x": 3031,
      "y": 480
    },
    {
      "x": 3041,
      "y": 458
    },
    {
      "x": 3397,
      "y": 575
    },
    {
      "x": 3382,
      "y": 553
    },
    {
      "x": 3755,
      "y": 456
    },
    {
      "x": 3781,
      "y": 434
    },
    {
      "x": 4058,
      "y": 510
    },
    {
      "x": 4058,
      "y": 488
    }
  ],
  "enemies": [
    {
      "x": 345,
      "y": 496,
      "kind": "walker"
    },
    {
      "x": 821,
      "y": 414,
      "kind": "flyer"
    },
    {
      "x": 1610,
      "y": 489,
      "kind": "walker"
    },
    {
      "x": 1930,
      "y": 572,
      "kind": "walker"
    },
    {
      "x": 3070,
      "y": 400,
      "kind": "flyer"
    },
    {
      "x": 3441,
      "y": 605,
      "kind": "walker"
    },
    {
      "x": 3810,
      "y": 486,
      "kind": "jumper"
    },
    {
      "x": 4073,
      "y": 540,
      "kind": "walker"
    }
  ]
}